Youtube_comment_word_frequency.py
Youtube_comment_word_frequency-0.0.3.dist-info/METADATA
Youtube_comment_word_frequency-0.0.3.dist-info/WHEEL
Youtube_comment_word_frequency-0.0.3.dist-info/entry_points.txt
Youtube_comment_word_frequency-0.0.3.dist-info/top_level.txt
Youtube_comment_word_frequency-0.0.3.dist-info/RECORD
