Metadata-Version: 2.1
Name: Youtube-comment-word-frequency
Version: 0.0.3
Summary: how to debut a PyPI for chemistry
Home-page: https://github.com/tsumiki207/Youtube_comment_word_frequency
Author: Nishiyama Mitsuki
Author-email: s2122047@stu.musashino-u.ac.jp
License: UNKNOWN
Project-URL: Bug Tracker, https://github.com/tsumiki207/Youtube_comment_word_frequency
Platform: UNKNOWN
Classifier: Programming Language :: Python :: 3
Classifier: License :: OSI Approved :: MIT License
Classifier: Operating System :: OS Independent
Requires-Python: >=3.7
